petroflow/__init__.py
petroflow/batchflow/__init__.py
petroflow/batchflow/setup.py
petroflow/batchflow/batchflow/__init__.py
petroflow/batchflow/batchflow/_const.py
petroflow/batchflow/batchflow/_fake.py
petroflow/batchflow/batchflow/base.py
petroflow/batchflow/batchflow/batch.py
petroflow/batchflow/batchflow/batch_image.py
petroflow/batchflow/batchflow/components.py
petroflow/batchflow/batchflow/config.py
petroflow/batchflow/batchflow/dataset.py
petroflow/batchflow/batchflow/decorators.py
petroflow/batchflow/batchflow/dsindex.py
petroflow/batchflow/batchflow/exceptions.py
petroflow/batchflow/batchflow/model_dir.py
petroflow/batchflow/batchflow/named_expr.py
petroflow/batchflow/batchflow/once_pipeline.py
petroflow/batchflow/batchflow/pipeline.py
petroflow/batchflow/batchflow/sampler.py
petroflow/batchflow/batchflow/utils.py
petroflow/batchflow/batchflow/variables.py
petroflow/batchflow/batchflow/models/__init__.py
petroflow/batchflow/batchflow/models/base.py
petroflow/batchflow/batchflow/models/sklearn.py
petroflow/batchflow/batchflow/models/utils.py
petroflow/batchflow/batchflow/models/keras/__init__.py
petroflow/batchflow/batchflow/models/keras/keras_model.py
petroflow/batchflow/batchflow/models/metrics/__init__.py
petroflow/batchflow/batchflow/models/metrics/base.py
petroflow/batchflow/batchflow/models/metrics/classify.py
petroflow/batchflow/batchflow/models/metrics/loss.py
petroflow/batchflow/batchflow/models/metrics/regression.py
petroflow/batchflow/batchflow/models/metrics/segment.py
petroflow/batchflow/batchflow/models/metrics/utils.py
petroflow/batchflow/batchflow/models/tf/__init__.py
petroflow/batchflow/batchflow/models/tf/base.py
petroflow/batchflow/batchflow/models/tf/deeplab.py
petroflow/batchflow/batchflow/models/tf/densenet.py
petroflow/batchflow/batchflow/models/tf/densenet_fc.py
petroflow/batchflow/batchflow/models/tf/efficientnet.py
petroflow/batchflow/batchflow/models/tf/encoder_decoder.py
petroflow/batchflow/batchflow/models/tf/faster_rcnn.py
petroflow-0.1.0.dist-info/LICENSE
petroflow-0.1.0.dist-info/METADATA
petroflow-0.1.0.dist-info/WHEEL
petroflow-0.1.0.dist-info/top_level.txt
petroflow-0.1.0.dist-info/RECORD
